binsreg/__init__.py
binsreg/binsglm.py
binsreg/binspwc.py
binsreg/binsqreg.py
binsreg/binsreg.py
binsreg/binsregselect.py
binsreg/binstest.py
binsreg/funs.py
binsreg-2.1.5.dist-info/METADATA
binsreg-2.1.5.dist-info/WHEEL
binsreg-2.1.5.dist-info/top_level.txt
binsreg-2.1.5.dist-info/RECORD
