Metadata-Version: 2.1
Name: binsreg
Version: 2.1.5
Summary: Implements binscatter methods, including partition selection, point estimation, pointwise and uniform inference methods, and graphical procedures.
Home-page: https://github.com/nppackages/binsreg
Author: Ricardo Masini
Author-email: rmasini@princeton.edu
Project-URL: Bug Tracker, https://github.com/nppackages/binsreg/issues
Classifier: Programming Language :: Python :: 3
Classifier: License :: OSI Approved :: MIT License
Classifier: Operating System :: OS Independent
Requires-Python: >=3.6
Requires-Dist: numpy
Requires-Dist: pandas >=2.0.0
Requires-Dist: scipy
Requires-Dist: statsmodels >=0.14.0
Requires-Dist: plotnine
